MANIFEST.in
setup.py
inasafe_cli/__init__.py
inasafe_cli/inasafe.py
inasafe_cli/test_inasafe.py
inasafe_cli/usage.txt
inasafe_cli.egg-info/PKG-INFO
inasafe_cli.egg-info/SOURCES.txt
inasafe_cli.egg-info/dependency_links.txt
inasafe_cli.egg-info/entry_points.txt
inasafe_cli.egg-info/requires.txt
inasafe_cli.egg-info/top_level.txt