Metadata-Version: 1.1
Name: inasafe-cli
Version: 1.0.6
Summary: Realistic natural hazard impact scenarios for better planning, preparedness and response activities.
Home-page: http://inasafe.org/
Author: InaSAFE Team
Author-email: info@inasafe.org
License: GPL
Platform: UNKNOWN
Classifier: Development Status :: 5 - Production/Stable
Classifier: Intended Audience :: Developers
Classifier: Intended Audience :: Science/Research
Classifier: License :: OSI Approved :: GNU General Public License v3 (GPLv3)
Classifier: Operating System :: OS Independent
Classifier: Programming Language :: Python
Classifier: Topic :: Scientific/Engineering :: GIS
